{"views":{"creds":{"map":"/*\n\tselects documents of type \"user\" by the key \"id\"\n\tall the listed once by the key \"user_id\"\n\t###\n\troutes do not return (with user 660...): \n\ti guess jetty *boils the heap... (there is not even an error message...\n\tmight also be \"node.js\" \"elastic\" (view)\n\t### \n*/\nfunction (doc, meta) {\n  if(\"user\" == doc.type){\n  \temit(meta.id, doc);  \n  }\n  else if(\"dog\" == doc.type\n          || \"notification\" == doc.type\n          || \"friendship\" == doc.type\n          || \"gassicall\" == doc.type\n          || \"poi\" == doc.type\n          || \"meetingpoint\" == doc.type\n          || \"photo\" == doc.type\n          || \"route\" == doc.type\n         )\n  {\n  \temit(doc.user_id, doc);\n  }\n}"},"friends":{"map":"function (doc, meta) {\n  if(doc.type == \"friendship\"){\n    \temit(doc.user_id, doc.friend_id);\n  }}\n   "},"gassicalls":{"map":"function (doc, meta) {\n  if(\"gassicall\" == doc.type){\n  emit(doc.user_id, doc);\n  }\n}"},"items":{"map":"function (doc, meta) {\n  emit([doc.user_id, doc.type], doc);\n}"},"notifications":{"map":"function (doc, meta) {\n  if(\"notification\" == doc.type){\n  emit(doc.user_id, doc);\n  }\n}"},"photos":{"map":"function (doc, meta) {\n  if(\"photo\" == doc.type){\n  emit(doc.user_id, doc);\n  }\n}"},"pois":{"map":"function (doc, meta) {\n  if(\"poi\" == doc.type){\n  \temit(doc.user_id, doc);\n  }\n}"},"resultlist":{"map":"function (doc, meta) {\n  emit(meta.id, doc);\n}"},"routes":{"map":"function (doc, meta) {\n  if(\"route\" == doc.type){\n    emit(doc.user_id, \n         {\n           \"created\": doc.created, \n           \"name\": doc.name, \n           \"length\": doc.length, \n           \"maps\": doc.maps, \n           \"begin_timestamp\": doc.begin_timestamp, \n           \"end_timestamp\": doc.end_timestamp, \n           \"user_id\": doc.user_id \n         }\n    \t);\n  };\n}"}}}